awth/__init__.py
awth/config.py
awth/constants.py
awth/help_text.py
awth/util.py
awth-0.1.0a6.dist-info/LICENSE
awth-0.1.0a6.dist-info/METADATA
awth-0.1.0a6.dist-info/WHEEL
awth-0.1.0a6.dist-info/entry_points.txt
awth-0.1.0a6.dist-info/RECORD
