Metadata-Version: 2.3
Name: awth
Version: 0.1.0a6
Summary: awth your way into aws, again, with mfa
License: MIT
Keywords: aws
Author: jessebot
Author-email: jessebot@linux.com
Requires-Python: >=3.12,<4.0
Classifier: Development Status :: 3 - Alpha
Classifier: License :: OSI Approved :: MIT License
Classifier: Operating System :: MacOS :: MacOS X
Classifier: Operating System :: POSIX :: Linux
Classifier: Programming Language :: Python :: 3
Classifier: Programming Language :: Python :: 3.12
Classifier: Programming Language :: Python :: 3.13
Requires-Dist: boto3 (>=1.38,<2.0)
Requires-Dist: click (>=8.1,<9.0)
Requires-Dist: keyring (>=25.6,<26.0)
Requires-Dist: rich (>=13.6,<14.0)
Requires-Dist: secretstorage (>=3.3,<4.0)
Project-URL: Bug Tracker, http://github.com/small-hack/awth/issues
Project-URL: Documentation, https://github.com/small-hack/awth
Project-URL: Repository, http://github.com/small-hack/awth
